anaconda_assistant_conda/__init__.py
anaconda_assistant_conda/_version.py
anaconda_assistant_conda/cli.py
anaconda_assistant_conda/config.py
anaconda_assistant_conda/core.py
anaconda_assistant_conda/get_clean_error_report_command.py
anaconda_assistant_conda/plugin.py
anaconda_assistant_conda/prompt_accept_terms.py
anaconda_assistant_conda/prompt_debug_config.py
anaconda_assistant_conda/rich_customizations/ansi_syntax_theme.py
anaconda_assistant_conda/rich_customizations/console_theme.py
anaconda_assistant_conda/rich_customizations/md.py
anaconda_assistant_conda-0.6.0.dist-info/METADATA
anaconda_assistant_conda-0.6.0.dist-info/WHEEL
anaconda_assistant_conda-0.6.0.dist-info/entry_points.txt
anaconda_assistant_conda-0.6.0.dist-info/licenses/LICENSE
anaconda_assistant_conda-0.6.0.dist-info/RECORD
