Metadata-Version: 2.4
Name: anaconda-assistant-conda
Version: 0.6.0
Summary: The Anaconda Assistant conda plugin
License: BSD-3-Clause
License-File: LICENSE
Requires-Python: >=3.10
Requires-Dist: anaconda-assistant-mcp
Requires-Dist: anaconda-assistant-sdk>=0.4
Requires-Dist: anaconda-auth>=0.8
Requires-Dist: anaconda-cli-base>=0.5
Requires-Dist: fastmcp==2.8.1
Requires-Dist: pydantic>=2
Requires-Dist: requests
Requires-Dist: rich
Requires-Dist: tomli
Requires-Dist: tomli-w
Provides-Extra: dev
Requires-Dist: anaconda-assistant-mcp; extra == 'dev'
Requires-Dist: mypy; extra == 'dev'
Requires-Dist: pytest; extra == 'dev'
Requires-Dist: pytest-cov; extra == 'dev'
Requires-Dist: pytest-mock; extra == 'dev'
Requires-Dist: responses; extra == 'dev'
Requires-Dist: tox; extra == 'dev'
Requires-Dist: types-requests; extra == 'dev'
Provides-Extra: publish
Requires-Dist: build; extra == 'publish'
Requires-Dist: twine; extra == 'publish'
Requires-Dist: wheel; extra == 'publish'
